Workbook

Sheet Итоги
A1: Финансовая модель «Партер»: итоги за три года
A2: Модель — сервисный сбор с покупателя (бизнес-решение 2026-10-02), организатор не платит; команда — только основатель; Казахстан, тенге. Все значения — формулы от листа «Допущения».
B3: Пессимистичный | E3: Базовый | H3: Оптимистичный
A4: Показатель | B4: Год 1 | C4: Год 2 | D4: Год 3 | E4: Год 1 | F4: Год 2 | G4: Год 3 | H4: Год 1 | I4: Год 2 | J4: Год 3
A5: Активных организаторов на конец года | B5: =План!N12 -> 13.101992 | C5: =План!Z12 -> 32.439488 | D5: =План!AL12 -> 50.377257 | E5: =План!N36 -> 28.30043 | F5: =План!Z36 -> 63.454099 | G5: =План!AL36 -> 102.55176 | H5: =План!N60 -> 49.697091 | I5: =План!Z60 -> 111.92383 | J5: =План!AL60 -> 182.32141
A6: Продано билетов | B6: =SUM(План!$C$14:$N$14) -> 8406.8944 | C6: =SUM(План!$O$14:$Z$14) -> 25732.632 | D6: =SUM(План!$AA$14:$AL$14) -> 44500.731 | E6: =SUM(План!$C$38:$N$38) -> 25970.392 | F6: =SUM(План!$O$38:$Z$38) -> 74472.31 | G6: =SUM(План!$AA$38:$AL$38) -> 130526.8 | H6: =SUM(План!$C$62:$N$62) -> 76416.397 | I6: =SUM(План!$O$62:$Z$62) -> 222037.38 | J6: =SUM(План!$AA$62:$AL$62) -> 392812.7
A7: Оборот билетов (GMV), ₸ | B7: =SUM(План!$C$16:$N$16) -> 37831025 | C7: =SUM(План!$O$16:$Z$16) -> 1.1579684e+08 | D7: =SUM(План!$AA$16:$AL$16) -> 2.0025329e+08 | E7: =SUM(План!$C$40:$N$40) -> 1.4024012e+08 | F7: =SUM(План!$O$40:$Z$40) -> 4.0215047e+08 | G7: =SUM(План!$AA$40:$AL$40) -> 7.0484471e+08 | H7: =SUM(План!$C$64:$N$64) -> 4.814233e+08 | I7: =SUM(План!$O$64:$Z$64) -> 1.3988355e+09 | J7: =SUM(План!$AA$64:$AL$64) -> 2.47472e+09
A8: Выручка, ₸ | B8: =SUM(План!$C$17:$N$17) -> 1834804.7 | C8: =SUM(План!$O$17:$Z$17) -> 5616147 | D8: =SUM(План!$AA$17:$AL$17) -> 9712284.5 | E8: =SUM(План!$C$41:$N$41) -> 6801645.8 | F8: =SUM(План!$O$41:$Z$41) -> 19504298 | G8: =SUM(План!$AA$41:$AL$41) -> 34184968 | H8: =SUM(План!$C$65:$N$65) -> 23349030 | I8: =SUM(План!$O$65:$Z$65) -> 67843522 | J8: =SUM(План!$AA$65:$AL$65) -> 1.2002392e+08
A9: Маржинальная прибыль, ₸ | B9: =SUM(План!$C$21:$N$21) -> 642244.7 | C9: =SUM(План!$O$21:$Z$21) -> 1965844.4 | D9: =SUM(План!$AA$21:$AL$21) -> 3399633.3 | E9: =SUM(План!$C$45:$N$45) -> 3194981.6 | F9: =SUM(План!$O$45:$Z$45) -> 9161881.4 | G9: =SUM(План!$AA$45:$AL$45) -> 16057929 | H9: =SUM(План!$C$69:$N$69) -> 13686406 | I9: =SUM(План!$O$69:$Z$69) -> 39767561 | J9: =SUM(План!$AA$69:$AL$69) -> 70353934
A10: Постоянные расходы и маркетинг, ₸ | B10: =SUM(План!$C$26:$N$26) -> 5600000 | C10: =SUM(План!$O$26:$Z$26) -> 12720000 | D10: =SUM(План!$AA$26:$AL$26) -> 18480000 | E10: =SUM(План!$C$50:$N$50) -> 7400000 | F10: =SUM(План!$O$50:$Z$50) -> 14520000 | G10: =SUM(План!$AA$50:$AL$50) -> 21480000 | H10: =SUM(План!$C$74:$N$74) -> 8000000 | I10: =SUM(План!$O$74:$Z$74) -> 15120000 | J10: =SUM(План!$AA$74:$AL$74) -> 22080000
A11: Операционная прибыль, ₸ | B11: =SUM(План!$C$27:$N$27) -> -4957755.3 | C11: =SUM(План!$O$27:$Z$27) -> -10754156 | D11: =SUM(План!$AA$27:$AL$27) -> -15080367 | E11: =SUM(План!$C$51:$N$51) -> -4205018.4 | F11: =SUM(План!$O$51:$Z$51) -> -5358118.6 | G11: =SUM(План!$AA$51:$AL$51) -> -5422071.2 | H11: =SUM(План!$C$75:$N$75) -> 5686405.9 | I11: =SUM(План!$O$75:$Z$75) -> 24647561 | J11: =SUM(План!$AA$75:$AL$75) -> 48273934
A12: Накопленный поток на конец года, ₸ | B12: =План!N28 -> -4957755.3 | C12: =План!Z28 -> -15711911 | D12: =План!AL28 -> -30792278 | E12: =План!N52 -> -4205018.4 | F12: =План!Z52 -> -9563137 | G12: =План!AL52 -> -14985208 | H12: =План!N76 -> 5686405.9 | I12: =План!Z76 -> 30333967 | J12: =План!AL76 -> 78607901
A14: Ключевые выводы | B14: Пессимистичный | E14: Базовый | H14: Оптимистичный
A15: Первый месяц с операционной прибылью | B15: =IF(COUNT(План!$C$29:$AL$29)=0,"не достигнут",MIN(План!$C$29:$AL$29)) -> не достигнут | E15: =IF(COUNT(План!$C$53:$AL$53)=0,"не достигнут",MIN(План!$C$53:$AL$53)) -> 31 | H15: =IF(COUNT(План!$C$77:$AL$77)=0,"не достигнут",MIN(План!$C$77:$AL$77)) -> 4
A16: Месяц, с которого накопленный поток ≥ 0 (окупаемость) | B16: =IF(COUNT(План!$C$30:$AL$30)=0,"за 3 года нет",MIN(План!$C$30:$AL$30)) -> за 3 года нет | E16: =IF(COUNT(План!$C$54:$AL$54)=0,"за 3 года нет",MIN(План!$C$54:$AL$54)) -> за 3 года нет | H16: =IF(COUNT(План!$C$78:$AL$78)=0,"за 3 года нет",MIN(План!$C$78:$AL$78)) -> 7
A17: Нужно вложить до окупаемости (минимум накопленного потока), ₸ | B17: =-MIN(0,MIN(План!$C$28:$AL$28)) -> 30792278 | E17: =-MIN(0,MIN(План!$C$52:$AL$52)) -> 14985208 | H17: =-MIN(0,MIN(План!$C$76:$AL$76)) -> 1851111.8
A18: Выручка за 3 года, ₸ | B18: =SUM(План!$C$17:$AL$17) -> 17163236 | E18: =SUM(План!$C$41:$AL$41) -> 60490912 | H18: =SUM(План!$C$65:$AL$65) -> 2.1121647e+08
A19: Операционная прибыль за 3 года, ₸ | B19: =SUM(План!$C$27:$AL$27) -> -30792278 | E19: =SUM(План!$C$51:$AL$51) -> -14985208 | H19: =SUM(План!$C$75:$AL$75) -> 78607901
A20: LTV / CAC | B20: ='Юнит-экономика'!C21 -> 0.53953969 | E20: ='Юнит-экономика'!D21 -> 2.2654642 | H20: ='Юнит-экономика'!E21 -> 10.842128

Sheet Юнит-экономика
A1: Юнит-экономика: один билет и один организатор
A2: Цены и ставки — из листа «Допущения»; маржа на билет учитывает бесплатные билеты и возвраты.
B4: На один проданный билет | C4: Пессимистичный | D4: Базовый | E4: Оптимистичный
B5: Цена билета, ₸ | C5: =Допущения!$C$22 -> 5000 | D5: =Допущения!$D$22 -> 6000 | E5: =Допущения!$E$22 -> 7000
B6: Сервисный сбор и комиссия с платного билета, ₸ | C6: =C5*(Допущения!$C$6+Допущения!$C$7) -> 250 | D6: =D5*(Допущения!$C$6+Допущения!$C$7) -> 300 | E6: =E5*(Допущения!$C$6+Допущения!$C$7) -> 350
B7: Средняя выручка на проданный билет, ₸ | C7: =C6*(1-Допущения!$C$12)*(1-Допущения!$C$13) -> 218.25 | D7: =D6*(1-Допущения!$C$12)*(1-Допущения!$C$13) -> 261.9 | E7: =E6*(1-Допущения!$C$12)*(1-Допущения!$C$13) -> 305.55 | F7: с учётом бесплатных билетов и возвратов
B8: Эквайринг на проданный билет, ₸ | C8: =C5*(1+Допущения!$C$6)*Допущения!$C$23*(1-Допущения!$C$12) -> 118.125 | D8: =D5*(1+Допущения!$C$6)*Допущения!$D$23*(1-Допущения!$C$12) -> 113.4 | E8: =E5*(1+Допущения!$C$6)*Допущения!$E$23*(1-Допущения!$C$12) -> 99.225 | F8: с суммы оплаты, включая сбор; при возврате не возвращается
B9: SMS и инфраструктура на билет, ₸ | C9: =Допущения!$C$10/Допущения!$C$9+Допущения!$C$11 -> 15 | D9: =Допущения!$C$10/Допущения!$C$9+Допущения!$C$11 -> 15 | E9: =Допущения!$C$10/Допущения!$C$9+Допущения!$C$11 -> 15
B10: Налог, ₸ | C10: =C7*Допущения!$C$8 -> 8.73 | D10: =D7*Допущения!$C$8 -> 10.476 | E10: =E7*Допущения!$C$8 -> 12.222
B11: Маржа на проданный билет, ₸ | C11: =C7-C8-C9-C10 -> 76.395 | D11: =D7-D8-D9-D10 -> 123.024 | E11: =E7-E8-E9-E10 -> 179.103
B12: Маржа, % от цены билета | C12: =IF(C5=0,0,C11/C5) -> 0.015279 | D12: =IF(D5=0,0,D11/D5) -> 0.020504 | E12: =IF(E5=0,0,E11/E5) -> 0.025586143 | F12: в spec.md было ~2% при сборе 5% и эквайринге 2,5%
B14: На одного организатора
B15: Билетов в месяц (в среднем по году, с сезонностью) | C15: =Допущения!$C$28*Допущения!$C$29*AVERAGE(Допущения!$C$34:$N$34) -> 84.75 | D15: =Допущения!$D$28*Допущения!$D$29*AVERAGE(Допущения!$C$34:$N$34) -> 124.3 | E15: =Допущения!$E$28*Допущения!$E$29*AVERAGE(Допущения!$C$34:$N$34) -> 211.875
B16: Маржа с организатора в месяц, ₸ | C16: =C15*C11 -> 6474.4762 | D16: =D15*D11 -> 15291.883 | E16: =E15*E11 -> 37947.448
B17: Отток в месяц | C17: =Допущения!$C$27 -> 0.06 | D17: =Допущения!$D$27 -> 0.045 | E17: =Допущения!$E$27 -> 0.035
B18: Средний срок жизни организатора, мес | C18: =IF(C17=0,0,1/C17) -> 16.666667 | D18: =IF(D17=0,0,1/D17) -> 22.222222 | E18: =IF(E17=0,0,1/E17) -> 28.571429 | F18: 1 / отток
B19: LTV (маржа за срок жизни), ₸ | C19: =C16*C18 -> 107907.94 | D19: =D16*D18 -> 339819.63 | E19: =E16*E18 -> 1084212.8
B20: CAC, ₸ | C20: =Допущения!$C$30 -> 200000 | D20: =Допущения!$D$30 -> 150000 | E20: =Допущения!$E$30 -> 100000
B21: LTV / CAC | C21: =IF(C20=0,0,C19/C20) -> 0.53953969 | D21: =IF(D20=0,0,D19/D20) -> 2.2654642 | E21: =IF(E20=0,0,E19/E20) -> 10.842128 | F21: больше 3x — привлечение окупается с запасом
B22: Окупаемость привлечения, мес | C22: =IF(C16=0,0,C20/C16) -> 30.89053 | D22: =IF(D16=0,0,D20/D16) -> 9.8091254 | E22: =IF(E16=0,0,E20/E16) -> 2.6352233 | F22: CAC / маржа в месяц
B23: Организаторов для безубыточности во 2-м году | C23: =IF(C16=0,0,(Допущения!$D$18+Допущения!$C$15+Допущения!$D$19)/C16) -> 71.048218 | D23: =IF(D16=0,0,(Допущения!$D$18+Допущения!$C$15+Допущения!$D$19)/D16) -> 30.081318 | E23: =IF(E16=0,0,(Допущения!$D$18+Допущения!$C$15+Допущения!$D$19)/E16) -> 12.122027 | F23: постоянные расходы 2-го года без маркетинга / маржа с организатора

Sheet Допущения
A1: Финансовая модель «Партер» — допущения
A2: Синие числа — вводимые значения, их можно менять; жёлтым выделены ключевые бизнес-параметры. Все остальные листы считаются формулами от этого листа. Суммы — в тенге, проценты — доли.
B4: Общие параметры | C4: Значение | G4: Источник / обоснование
B5: Первый месяц модели | C5: 46539 | G5: Запуск после защиты диплома (май 2027). Допущение.
B6: Сервисный сбор с покупателя | C6: 0.05 | F6: от цены | G6: Бизнес-решение 2026-10-02: 5% (сначала 7%, снижено владельцем продукта). Рынок ~10%. В продукте — SERVICE_FEE_BPS, ADR 019.
B7: Комиссия с организатора | C7: 0 | F7: от цены | G7: Бизнес-решение 2026-10-02: организатор не платит.
B8: Налог (упрощённый режим, ИП) | C8: 0.04 | F8: от дохода | G8: Базовая ставка 4% по Налоговому кодексу РК с 2026; акимат может снизить до 2%. Доход — только сбор: нужна агентская схема (лист «Риски»).
B9: Билетов в одном заказе | C9: 2 | F9: шт. | G9: Допущение: пара — типичный заказ на концерт/стендап.
B10: SMS с кодом входа на заказ | C10: 20 | F10: ₸ | G10: Допущение по местным SMS-агрегаторам; международные шлюзы дороже (~€0,14). Код нужен при входе, не на каждый заказ — консервативно.
B11: Инфраструктура и письма на билет | C11: 5 | F11: ₸ | G11: Допущение: почта, хранилище, вычисления сверх фиксированного хостинга.
B12: Доля бесплатных билетов | C12: 0.1 | F12: от проданных | G12: Бесплатные билеты есть в продукте; сбор с них не берётся. Допущение.
B13: Доля возвращённых билетов | C13: 0.03 | F13: от платных | G13: Допущение. С запасом: в продукте сбор возвращается только при отмене события, при возврате по желанию покупателя он остаётся (ADR 019); эквайринг не возвращается.
B14: Юр. сопровождение запуска (разово, 1-й месяц) | C14: 800000 | F14: ₸ | G14: Агентский договор, оферта, проверка требований к платёжной деятельности. Допущение.
B15: Бухгалтерия и юрист, в месяц | C15: 40000 | F15: ₸/мес | G15: Допущение: аутсорс для ИП.
B17: По годам | C17: Год 1 | D17: Год 2 | E17: Год 3
B18: Хостинг и сервисы, в месяц | C18: 60000 | D18: 120000 | E18: 200000 | F18: ₸/мес | G18: Допущение: VPS + управляемые PostgreSQL/Redis, рост с нагрузкой.
B19: Выплата основателю, в месяц | C19: 0 | D19: 300000 | E19: 500000 | F19: ₸/мес | G19: Бизнес-решение: команда — только основатель. Суммы выплат — допущение, уточнить.
B21: Сценарии | C21: Пессимистичный | D21: Базовый | E21: Оптимистичный
B22: Средняя цена билета | C22: 5000 | D22: 6000 | E22: 7000 | F22: ₸ | G22: МСБ-сегмент дешевле крупных концертов. Ориентир: средний чек Ticketon 2021 — $11,9 ≈ 5 700 ₸ (spec.md).
B23: Эквайринг (от суммы оплаты) | C23: 0.025 | D23: 0.02 | E23: 0.015 | F23: от оплаты | G23: Kaspi Pay ~1–1,5%, Halyk ePay 2,5–3% для карт других банков (finkaz.kz, halykbank.kz, 2026).
B24: Новых организаторов в месяц, год 1 | C24: 1.5 | D24: 3 | E24: 5 | F24: шт./мес | G24: Прямые продажи основателя + бесплатное первое событие (spec.md: первые 20–50 организаторов).
B25: Новых организаторов в месяц, год 2 | C25: 3 | D25: 5 | E25: 8 | F25: шт./мес | G25: Рекомендации, второй город. Допущение.
B26: Новых организаторов в месяц, год 3 | C26: 4 | D26: 7 | E26: 11 | F26: шт./мес | G26: Другие города Казахстана. Допущение.
B27: Отток организаторов в месяц | C27: 0.06 | D27: 0.045 | E27: 0.035 | F27: от активных | G27: Допущение: для SaaS МСБ обычно 3–7% в месяц.
B28: Событий на организатора в месяц | C28: 1 | D28: 1.2 | E28: 1.5 | F28: шт. | G28: Стендап-клуб — еженедельно, конференция — раз в квартал; среднее. Допущение.
B29: Продано билетов на событие | C29: 90 | D29: 110 | E29: 150 | F29: шт. | G29: Малые и средние залы. Допущение.
B30: Стоимость привлечения организатора (CAC) | C30: 200000 | D30: 150000 | E30: 100000 | F30: ₸ | G30: Реклама, встречи, время на продажу, бесплатное первое событие. Допущение: для B2B-продаж МСБ дороже, чем кажется.
B32: Сезонность (1,0 — обычный месяц)
C33: янв | D33: фев | E33: мар | F33: апр | G33: май | H33: июн | I33: июл | J33: авг | K33: сен | L33: окт | M33: ноя | N33: дек
B34: Коэффициент | C34: 0.8 | D34: 0.9 | E34: 1 | F34: 1 | G34: 1 | H34: 0.8 | I34: 0.6 | J34: 0.6 | K34: 1 | L34: 1.1 | M34: 1.2 | N34: 1.3
B35: Летом залы пустеют, к Новому году — пик. Допущение.

Sheet План
A1: План на 36 месяцев по трём сценариям
A2: Все ячейки — формулы от листа «Допущения». Суммы в тенге.
A4: Месяц | C4: 1 | D4: 2 | E4: 3 | F4: 4 | G4: 5 | H4: 6 | I4: 7 | J4: 8 | K4: 9 | L4: 10 | M4: 11 | N4: 12 | O4: 13 | P4: 14 | Q4: 15 | R4: 16 | S4: 17 | T4: 18 | U4: 19 | V4: 20 | W4: 21 | X4: 22 | Y4: 23 | Z4: 24 | AA4: 25 | AB4: 26 | AC4: 27 | AD4: 28 | AE4: 29 | AF4: 30 | AG4: 31 | AH4: 32 | AI4: 33 | AJ4: 34 | AK4: 35 | AL4: 36
A5: Дата | C5: =EDATE(Допущения!$C$5,0) -> 46539 | D5: =EDATE(Допущения!$C$5,1) -> 46569 | E5: =EDATE(Допущения!$C$5,2) -> 46600 | F5: =EDATE(Допущения!$C$5,3) -> 46631 | G5: =EDATE(Допущения!$C$5,4) -> 46661 | H5: =EDATE(Допущения!$C$5,5) -> 46692 | I5: =EDATE(Допущения!$C$5,6) -> 46722 | J5: =EDATE(Допущения!$C$5,7) -> 46753 | K5: =EDATE(Допущения!$C$5,8) -> 46784 | L5: =EDATE(Допущения!$C$5,9) -> 46813 | M5: =EDATE(Допущения!$C$5,10) -> 46844 | N5: =EDATE(Допущения!$C$5,11) -> 46874 | O5: =EDATE(Допущения!$C$5,12) -> 46905 | P5: =EDATE(Допущения!$C$5,13) -> 46935 | Q5: =EDATE(Допущения!$C$5,14) -> 46966 | R5: =EDATE(Допущения!$C$5,15) -> 46997 | S5: =EDATE(Допущения!$C$5,16) -> 47027 | T5: =EDATE(Допущения!$C$5,17) -> 47058 | U5: =EDATE(Допущения!$C$5,18) -> 47088 | V5: =EDATE(Допущения!$C$5,19) -> 47119 | W5: =EDATE(Допущения!$C$5,20) -> 47150 | X5: =EDATE(Допущения!$C$5,21) -> 47178 | Y5: =EDATE(Допущения!$C$5,22) -> 47209 | Z5: =EDATE(Допущения!$C$5,23) -> 47239 | AA5: =EDATE(Допущения!$C$5,24) -> 47270 | AB5: =EDATE(Допущения!$C$5,25) -> 47300 | AC5: =EDATE(Допущения!$C$5,26) -> 47331 | AD5: =EDATE(Допущения!$C$5,27) -> 47362 | AE5: =EDATE(Допущения!$C$5,28) -> 47392 | AF5: =EDATE(Допущения!$C$5,29) -> 47423 | AG5: =EDATE(Допущения!$C$5,30) -> 47453 | AH5: =EDATE(Допущения!$C$5,31) -> 47484 | AI5: =EDATE(Допущения!$C$5,32) -> 47515 | AJ5: =EDATE(Допущения!$C$5,33) -> 47543 | AK5: =EDATE(Допущения!$C$5,34) -> 47574 | AL5: =EDATE(Допущения!$C$5,35) -> 47604
A6: Год модели | C6: =INT((C4-1)/12)+1 -> 1 | D6: =INT((D4-1)/12)+1 -> 1 | E6: =INT((E4-1)/12)+1 -> 1 | F6: =INT((F4-1)/12)+1 -> 1 | G6: =INT((G4-1)/12)+1 -> 1 | H6: =INT((H4-1)/12)+1 -> 1 | I6: =INT((I4-1)/12)+1 -> 1 | J6: =INT((J4-1)/12)+1 -> 1 | ... AL6: =INT((AL4-1)/12)+1 -> 3
A7: Сезонность | C7: =INDEX(Допущения!$C$34:$N$34,MONTH(C5)) -> 0.8 | D7: =INDEX(Допущения!$C$34:$N$34,MONTH(D5)) -> 0.6 | E7: =INDEX(Допущения!$C$34:$N$34,MONTH(E5)) -> 0.6 | F7: =INDEX(Допущения!$C$34:$N$34,MONTH(F5)) -> 1 | G7: =INDEX(Допущения!$C$34:$N$34,MONTH(G5)) -> 1.1 | H7: =INDEX(Допущения!$C$34:$N$34,MONTH(H5)) -> 1.2 | I7: =INDEX(Допущения!$C$34:$N$34,MONTH(I5)) -> 1.3 | J7: =INDEX(Допущения!$C$34:$N$34,MONTH(J5)) -> 0.8 | ... AL7: =INDEX(Допущения!$C$34:$N$34,MONTH(AL5)) -> 1
A9: Сценарий: Пессимистичный
A10: Новые организаторы | B10: шт. | C10: =CHOOSE(C$6,Допущения!$C$24,Допущения!$C$25,Допущения!$C$26) -> 1.5 | D10: =CHOOSE(D$6,Допущения!$C$24,Допущения!$C$25,Допущения!$C$26) -> 1.5 | E10: =CHOOSE(E$6,Допущения!$C$24,Допущения!$C$25,Допущения!$C$26) -> 1.5 | F10: =CHOOSE(F$6,Допущения!$C$24,Допущения!$C$25,Допущения!$C$26) -> 1.5 | G10: =CHOOSE(G$6,Допущения!$C$24,Допущения!$C$25,Допущения!$C$26) -> 1.5 | H10: =CHOOSE(H$6,Допущения!$C$24,Допущения!$C$25,Допущения!$C$26) -> 1.5 | I10: =CHOOSE(I$6,Допущения!$C$24,Допущения!$C$25,Допущения!$C$26) -> 1.5 | J10: =CHOOSE(J$6,Допущения!$C$24,Допущения!$C$25,Допущения!$C$26) -> 1.5 | ... AL10: =CHOOSE(AL$6,Допущения!$C$24,Допущения!$C$25,Допущения!$C$26) -> 4
A11: Ушедшие организаторы | B11: шт. | C11: =0 -> 0 | D11: =C12*Допущения!$C$27 -> 0.09 | E11: =D12*Допущения!$C$27 -> 0.1746 | F11: =E12*Допущения!$C$27 -> 0.254124 | G11: =F12*Допущения!$C$27 -> 0.32887656 | H11: =G12*Допущения!$C$27 -> 0.39914397 | I11: =H12*Допущения!$C$27 -> 0.46519533 | J11: =I12*Допущения!$C$27 -> 0.52728361 | K11: =J12*Допущения!$C$27 -> 0.58564659 | ... AL11: =AK12*Допущения!$C$27 -> 2.9602505
A12: Активные организаторы на конец месяца | B12: шт. | C12: =C10 -> 1.5 | D12: =C12+D10-D11 -> 2.91 | E12: =D12+E10-E11 -> 4.2354 | F12: =E12+F10-F11 -> 5.481276 | G12: =F12+G10-G11 -> 6.6523994 | H12: =G12+H10-H11 -> 7.7532555 | I12: =H12+I10-I11 -> 8.7880601 | J12: =I12+J10-J11 -> 9.7607765 | K12: =J12+K10-K11 -> 10.67513 | ... AL12: =AK12+AL10-AL11 -> 50.377257
A13: Событий с продажей билетов | B13: шт. | C13: =C12*Допущения!$C$28*C$7 -> 1.2 | D13: =D12*Допущения!$C$28*D$7 -> 1.746 | E13: =E12*Допущения!$C$28*E$7 -> 2.54124 | F13: =F12*Допущения!$C$28*F$7 -> 5.481276 | G13: =G12*Допущения!$C$28*G$7 -> 7.3176394 | H13: =H12*Допущения!$C$28*H$7 -> 9.3039066 | I13: =I12*Допущения!$C$28*I$7 -> 11.424478 | J13: =J12*Допущения!$C$28*J$7 -> 7.8086212 | ... AL13: =AL12*Допущения!$C$28*AL$7 -> 50.377257
A14: Продано билетов | B14: шт. | C14: =C13*Допущения!$C$29 -> 108 | D14: =D13*Допущения!$C$29 -> 157.14 | E14: =E13*Допущения!$C$29 -> 228.7116 | F14: =F13*Допущения!$C$29 -> 493.31484 | G14: =G13*Допущения!$C$29 -> 658.58754 | H14: =H13*Допущения!$C$29 -> 837.35159 | I14: =I13*Допущения!$C$29 -> 1028.203 | J14: =J13*Допущения!$C$29 -> 702.77591 | ... AL14: =AL13*Допущения!$C$29 -> 4533.9532
A15: Платных билетов | B15: шт. | C15: =C14*(1-Допущения!$C$12) -> 97.2 | D15: =D14*(1-Допущения!$C$12) -> 141.426 | E15: =E14*(1-Допущения!$C$12) -> 205.84044 | F15: =F14*(1-Допущения!$C$12) -> 443.98336 | G15: =G14*(1-Допущения!$C$12) -> 592.72879 | H15: =H14*(1-Допущения!$C$12) -> 753.61643 | I15: =I14*(1-Допущения!$C$12) -> 925.38273 | J15: =J14*(1-Допущения!$C$12) -> 632.49832 | ... AL15: =AL14*(1-Допущения!$C$12) -> 4080.5578
A16: Оборот билетов организаторов (GMV) | B16: ₸ | C16: =C15*Допущения!$C$22 -> 486000 | D16: =D15*Допущения!$C$22 -> 707130 | E16: =E15*Допущения!$C$22 -> 1029202.2 | F16: =F15*Допущения!$C$22 -> 2219916.8 | G16: =G15*Допущения!$C$22 -> 2963644 | H16: =H15*Допущения!$C$22 -> 3768082.2 | I16: =I15*Допущения!$C$22 -> 4626913.7 | J16: =J15*Допущения!$C$22 -> 3162491.6 | ... AL16: =AL15*Допущения!$C$22 -> 20402789
A17: Выручка: сервисный сбор и комиссия | B17: ₸ | C17: =C16*(Допущения!$C$6+Допущения!$C$7)*(1-Допущения!$C$13) -> 23571 | D17: =D16*(Допущения!$C$6+Допущения!$C$7)*(1-Допущения!$C$13) -> 34295.805 | E17: =E16*(Допущения!$C$6+Допущения!$C$7)*(1-Допущения!$C$13) -> 49916.307 | F17: =F16*(Допущения!$C$6+Допущения!$C$7)*(1-Допущения!$C$13) -> 107665.96 | G17: =G16*(Допущения!$C$6+Допущения!$C$7)*(1-Допущения!$C$13) -> 143736.73 | H17: =H16*(Допущения!$C$6+Допущения!$C$7)*(1-Допущения!$C$13) -> 182751.98 | I17: =I16*(Допущения!$C$6+Допущения!$C$7)*(1-Допущения!$C$13) -> 224405.31 | J17: =J16*(Допущения!$C$6+Допущения!$C$7)*(1-Допущения!$C$13) -> 153380.84 | ... AL17: =AL16*(Допущения!$C$6+Допущения!$C$7)*(1-Допущения!$C$13) -> 989535.28
A18: Эквайринг | B18: ₸ | C18: =C16*(1+Допущения!$C$6)*Допущения!$C$23 -> 12757.5 | D18: =D16*(1+Допущения!$C$6)*Допущения!$C$23 -> 18562.162 | E18: =E16*(1+Допущения!$C$6)*Допущения!$C$23 -> 27016.558 | F18: =F16*(1+Допущения!$C$6)*Допущения!$C$23 -> 58272.815 | G18: =G16*(1+Допущения!$C$6)*Допущения!$C$23 -> 77795.654 | H18: =H16*(1+Допущения!$C$6)*Допущения!$C$23 -> 98912.157 | I18: =I16*(1+Допущения!$C$6)*Допущения!$C$23 -> 121456.48 | J18: =J16*(1+Допущения!$C$6)*Допущения!$C$23 -> 83015.404 | ... AL18: =AL16*(1+Допущения!$C$6)*Допущения!$C$23 -> 535573.22
A19: SMS и инфраструктура на билеты | B19: ₸ | C19: =C14/Допущения!$C$9*Допущения!$C$10+C14*Допущения!$C$11 -> 1620 | D19: =D14/Допущения!$C$9*Допущения!$C$10+D14*Допущения!$C$11 -> 2357.1 | E19: =E14/Допущения!$C$9*Допущения!$C$10+E14*Допущения!$C$11 -> 3430.674 | F19: =F14/Допущения!$C$9*Допущения!$C$10+F14*Допущения!$C$11 -> 7399.7226 | G19: =G14/Допущения!$C$9*Допущения!$C$10+G14*Допущения!$C$11 -> 9878.8132 | H19: =H14/Допущения!$C$9*Допущения!$C$10+H14*Допущения!$C$11 -> 12560.274 | I19: =I14/Допущения!$C$9*Допущения!$C$10+I14*Допущения!$C$11 -> 15423.046 | J19: =J14/Допущения!$C$9*Допущения!$C$10+J14*Допущения!$C$11 -> 10541.639 | ... AL19: =AL14/Допущения!$C$9*Допущения!$C$10+AL14*Допущения!$C$11 -> 68009.297
A20: Налог с выручки | B20: ₸ | C20: =C17*Допущения!$C$8 -> 942.84 | D20: =D17*Допущения!$C$8 -> 1371.8322 | E20: =E17*Допущения!$C$8 -> 1996.6523 | F20: =F17*Допущения!$C$8 -> 4306.6386 | G20: =G17*Допущения!$C$8 -> 5749.4693 | H20: =H17*Допущения!$C$8 -> 7310.0794 | I20: =I17*Допущения!$C$8 -> 8976.2125 | J20: =J17*Допущения!$C$8 -> 6135.2337 | ... AL20: =AL17*Допущения!$C$8 -> 39581.411
A21: Маржинальная прибыль | B21: ₸ | C21: =C17-C18-C19-C20 -> 8250.66 | D21: =D17-D18-D19-D20 -> 12004.71 | E21: =E17-E18-E19-E20 -> 17472.423 | F21: =F17-F18-F19-F20 -> 37686.787 | G21: =G17-G18-G19-G20 -> 50312.795 | H21: =H17-H18-H19-H20 -> 63969.475 | I21: =I17-I18-I19-I20 -> 78549.571 | J21: =J17-J18-J19-J20 -> 53688.566 | ... AL21: =AL17-AL18-AL19-AL20 -> 346371.35
A22: Привлечение организаторов (CAC × новые) | B22: ₸ | C22: =C10*Допущения!$C$30 -> 300000 | D22: =D10*Допущения!$C$30 -> 300000 | E22: =E10*Допущения!$C$30 -> 300000 | F22: =F10*Допущения!$C$30 -> 300000 | G22: =G10*Допущения!$C$30 -> 300000 | H22: =H10*Допущения!$C$30 -> 300000 | I22: =I10*Допущения!$C$30 -> 300000 | J22: =J10*Допущения!$C$30 -> 300000 | ... AL22: =AL10*Допущения!$C$30 -> 800000
A23: Хостинг и сервисы | B23: ₸ | C23: =CHOOSE(C$6,Допущения!$C$18,Допущения!$D$18,Допущения!$E$18) -> 60000 | D23: =CHOOSE(D$6,Допущения!$C$18,Допущения!$D$18,Допущения!$E$18) -> 60000 | E23: =CHOOSE(E$6,Допущения!$C$18,Допущения!$D$18,Допущения!$E$18) -> 60000 | F23: =CHOOSE(F$6,Допущения!$C$18,Допущения!$D$18,Допущения!$E$18) -> 60000 | G23: =CHOOSE(G$6,Допущения!$C$18,Допущения!$D$18,Допущения!$E$18) -> 60000 | H23: =CHOOSE(H$6,Допущения!$C$18,Допущения!$D$18,Допущения!$E$18) -> 60000 | I23: =CHOOSE(I$6,Допущения!$C$18,Допущения!$D$18,Допущения!$E$18) -> 60000 | J23: =CHOOSE(J$6,Допущения!$C$18,Допущения!$D$18,Допущения!$E$18) -> 60000 | ... AL23: =CHOOSE(AL$6,Допущения!$C$18,Допущения!$D$18,Допущения!$E$18) -> 200000
A24: Бухгалтерия, юрист, запуск | B24: ₸ | C24: =Допущения!$C$15+IF(C$4=1,Допущения!$C$14,0) -> 840000 | D24: =Допущения!$C$15+IF(D$4=1,Допущения!$C$14,0) -> 40000 | E24: =Допущения!$C$15+IF(E$4=1,Допущения!$C$14,0) -> 40000 | F24: =Допущения!$C$15+IF(F$4=1,Допущения!$C$14,0) -> 40000 | G24: =Допущения!$C$15+IF(G$4=1,Допущения!$C$14,0) -> 40000 | H24: =Допущения!$C$15+IF(H$4=1,Допущения!$C$14,0) -> 40000 | I24: =Допущения!$C$15+IF(I$4=1,Допущения!$C$14,0) -> 40000 | J24: =Допущения!$C$15+IF(J$4=1,Допущения!$C$14,0) -> 40000 | ... AL24: =Допущения!$C$15+IF(AL$4=1,Допущения!$C$14,0) -> 40000
A25: Выплата основателю | B25: ₸ | C25: =CHOOSE(C$6,Допущения!$C$19,Допущения!$D$19,Допущения!$E$19) -> 0 | D25: =CHOOSE(D$6,Допущения!$C$19,Допущения!$D$19,Допущения!$E$19) -> 0 | E25: =CHOOSE(E$6,Допущения!$C$19,Допущения!$D$19,Допущения!$E$19) -> 0 | F25: =CHOOSE(F$6,Допущения!$C$19,Допущения!$D$19,Допущения!$E$19) -> 0 | G25: =CHOOSE(G$6,Допущения!$C$19,Допущения!$D$19,Допущения!$E$19) -> 0 | H25: =CHOOSE(H$6,Допущения!$C$19,Допущения!$D$19,Допущения!$E$19) -> 0 | I25: =CHOOSE(I$6,Допущения!$C$19,Допущения!$D$19,Допущения!$E$19) -> 0 | J25: =CHOOSE(J$6,Допущения!$C$19,Допущения!$D$19,Допущения!$E$19) -> 0 | ... AL25: =CHOOSE(AL$6,Допущения!$C$19,Допущения!$D$19,Допущения!$E$19) -> 500000
A26: Постоянные расходы и маркетинг | B26: ₸ | C26: =SUM(C22:C25) -> 1200000 | D26: =SUM(D22:D25) -> 400000 | E26: =SUM(E22:E25) -> 400000 | F26: =SUM(F22:F25) -> 400000 | G26: =SUM(G22:G25) -> 400000 | H26: =SUM(H22:H25) -> 400000 | I26: =SUM(I22:I25) -> 400000 | J26: =SUM(J22:J25) -> 400000 | ... AL26: =SUM(AL22:AL25) -> 1540000
A27: Операционная прибыль | B27: ₸ | C27: =C21-C26 -> -1191749.3 | D27: =D21-D26 -> -387995.29 | E27: =E21-E26 -> -382527.58 | F27: =F21-F26 -> -362313.21 | G27: =G21-G26 -> -349687.2 | H27: =H21-H26 -> -336030.53 | I27: =I21-I26 -> -321450.43 | J27: =J21-J26 -> -346311.43 | ... AL27: =AL21-AL26 -> -1193628.6
A28: Накопленный денежный поток | B28: ₸ | C28: =C27 -> -1191749.3 | D28: =C28+D27 -> -1579744.6 | E28: =D28+E27 -> -1962272.2 | F28: =E28+F27 -> -2324585.4 | G28: =F28+G27 -> -2674272.6 | H28: =G28+H27 -> -3010303.1 | I28: =H28+I27 -> -3331753.6 | J28: =I28+J27 -> -3678065 | K28: =J28+K27 -> -4012007.4 | ... AL28: =AK28+AL27 -> -30792278
A29: служебная: месяц с прибылью | C29: =IF(C27>0,C$4,"") | D29: =IF(D27>0,D$4,"") | E29: =IF(E27>0,E$4,"") | F29: =IF(F27>0,F$4,"") | G29: =IF(G27>0,G$4,"") | H29: =IF(H27>0,H$4,"") | I29: =IF(I27>0,I$4,"") | J29: =IF(J27>0,J$4,"") | ... AL29: =IF(AL27>0,AL$4,"")
A30: служебная: месяц с накопленным потоком ≥ 0 | C30: =IF(C28>=0,C$4,"") | D30: =IF(D28>=0,D$4,"") | E30: =IF(E28>=0,E$4,"") | F30: =IF(F28>=0,F$4,"") | G30: =IF(G28>=0,G$4,"") | H30: =IF(H28>=0,H$4,"") | I30: =IF(I28>=0,I$4,"") | J30: =IF(J28>=0,J$4,"") | ... AL30: =IF(AL28>=0,AL$4,"")
A33: Сценарий: Базовый
A34: Новые организаторы | B34: шт. | C34: =CHOOSE(C$6,Допущения!$D$24,Допущения!$D$25,Допущения!$D$26) -> 3 | D34: =CHOOSE(D$6,Допущения!$D$24,Допущения!$D$25,Допущения!$D$26) -> 3 | E34: =CHOOSE(E$6,Допущения!$D$24,Допущения!$D$25,Допущения!$D$26) -> 3 | F34: =CHOOSE(F$6,Допущения!$D$24,Допущения!$D$25,Допущения!$D$26) -> 3 | G34: =CHOOSE(G$6,Допущения!$D$24,Допущения!$D$25,Допущения!$D$26) -> 3 | H34: =CHOOSE(H$6,Допущения!$D$24,Допущения!$D$25,Допущения!$D$26) -> 3 | I34: =CHOOSE(I$6,Допущения!$D$24,Допущения!$D$25,Допущения!$D$26) -> 3 | J34: =CHOOSE(J$6,Допущения!$D$24,Допущения!$D$25,Допущения!$D$26) -> 3 | ... AL34: =CHOOSE(AL$6,Допущения!$D$24,Допущения!$D$25,Допущения!$D$26) -> 7
A35: Ушедшие организаторы | B35: шт. | C35: =0 -> 0 | D35: =C36*Допущения!$D$27 -> 0.135 | E35: =D36*Допущения!$D$27 -> 0.263925 | F35: =E36*Допущения!$D$27 -> 0.38704838 | G35: =F36*Допущения!$D$27 -> 0.5046312 | H35: =G36*Допущения!$D$27 -> 0.61692279 | I35: =H36*Допущения!$D$27 -> 0.72416127 | J35: =I36*Допущения!$D$27 -> 0.82657401 | K35: =J36*Допущения!$D$27 -> 0.92437818 | ... AL35: =AK36*Допущения!$D$27 -> 4.502439
A36: Активные организаторы на конец месяца | B36: шт. | C36: =C34 -> 3 | D36: =C36+D34-D35 -> 5.865 | E36: =D36+E34-E35 -> 8.601075 | F36: =E36+F34-F35 -> 11.214027 | G36: =F36+G34-G35 -> 13.709395 | H36: =G36+H34-H35 -> 16.092473 | I36: =H36+I34-I35 -> 18.368311 | J36: =I36+J34-J35 -> 20.541737 | K36: =J36+K34-K35 -> 22.617359 | ... AL36: =AK36+AL34-AL35 -> 102.55176
A37: Событий с продажей билетов | B37: шт. | C37: =C36*Допущения!$D$28*C$7 -> 2.88 | D37: =D36*Допущения!$D$28*D$7 -> 4.2228 | E37: =E36*Допущения!$D$28*E$7 -> 6.192774 | F37: =F36*Допущения!$D$28*F$7 -> 13.456832 | G37: =G36*Допущения!$D$28*G$7 -> 18.096402 | H37: =H36*Допущения!$D$28*H$7 -> 23.173161 | I37: =I36*Допущения!$D$28*I$7 -> 28.654566 | J37: =J36*Допущения!$D$28*J$7 -> 19.720068 | ... AL37: =AL36*Допущения!$D$28*AL$7 -> 123.06211
A38: Продано билетов | B38: шт. | C38: =C37*Допущения!$D$29 -> 316.8 | D38: =D37*Допущения!$D$29 -> 464.508 | E38: =E37*Допущения!$D$29 -> 681.20514 | F38: =F37*Допущения!$D$29 -> 1480.2515 | G38: =G37*Допущения!$D$29 -> 1990.6042 | H38: =H37*Допущения!$D$29 -> 2549.0477 | I38: =I37*Допущения!$D$29 -> 3152.0022 | J38: =J37*Допущения!$D$29 -> 2169.2075 | ... AL38: =AL37*Допущения!$D$29 -> 13536.832
A39: Платных билетов | B39: шт. | C39: =C38*(1-Допущения!$C$12) -> 285.12 | D39: =D38*(1-Допущения!$C$12) -> 418.0572 | E39: =E38*(1-Допущения!$C$12) -> 613.08463 | F39: =F38*(1-Допущения!$C$12) -> 1332.2264 | G39: =G38*(1-Допущения!$C$12) -> 1791.5438 | H39: =H38*(1-Допущения!$C$12) -> 2294.1429 | I39: =I38*(1-Допущения!$C$12) -> 2836.802 | J39: =J38*(1-Допущения!$C$12) -> 1952.2867 | ... AL39: =AL38*(1-Допущения!$C$12) -> 12183.149
A40: Оборот билетов организаторов (GMV) | B40: ₸ | C40: =C39*Допущения!$D$22 -> 1710720 | D40: =D39*Допущения!$D$22 -> 2508343.2 | E40: =E39*Допущения!$D$22 -> 3678507.8 | F40: =F39*Допущения!$D$22 -> 7993358.2 | G40: =G39*Допущения!$D$22 -> 10749263 | H40: =H39*Допущения!$D$22 -> 13764857 | I40: =I39*Допущения!$D$22 -> 17020812 | J40: =J39*Допущения!$D$22 -> 11713720 | ... AL40: =AL39*Допущения!$D$22 -> 73098895
A41: Выручка: сервисный сбор и комиссия | B41: ₸ | C41: =C40*(Допущения!$C$6+Допущения!$C$7)*(1-Допущения!$C$13) -> 82969.92 | D41: =D40*(Допущения!$C$6+Допущения!$C$7)*(1-Допущения!$C$13) -> 121654.65 | E41: =E40*(Допущения!$C$6+Допущения!$C$7)*(1-Допущения!$C$13) -> 178407.63 | F41: =F40*(Допущения!$C$6+Допущения!$C$7)*(1-Допущения!$C$13) -> 387677.87 | G41: =G40*(Допущения!$C$6+Допущения!$C$7)*(1-Допущения!$C$13) -> 521339.24 | H41: =H40*(Допущения!$C$6+Допущения!$C$7)*(1-Допущения!$C$13) -> 667595.58 | I41: =I40*(Допущения!$C$6+Допущения!$C$7)*(1-Допущения!$C$13) -> 825509.38 | J41: =J40*(Допущения!$C$6+Допущения!$C$7)*(1-Допущения!$C$13) -> 568115.43 | ... AL41: =AL40*(Допущения!$C$6+Допущения!$C$7)*(1-Допущения!$C$13) -> 3545296.4
A42: Эквайринг | B42: ₸ | C42: =C40*(1+Допущения!$C$6)*Допущения!$D$23 -> 35925.12 | D42: =D40*(1+Допущения!$C$6)*Допущения!$D$23 -> 52675.207 | E42: =E40*(1+Допущения!$C$6)*Допущения!$D$23 -> 77248.663 | F42: =F40*(1+Допущения!$C$6)*Допущения!$D$23 -> 167860.52 | G42: =G40*(1+Допущения!$C$6)*Допущения!$D$23 -> 225734.52 | H42: =H40*(1+Допущения!$C$6)*Допущения!$D$23 -> 289062.01 | I42: =I40*(1+Допущения!$C$6)*Допущения!$D$23 -> 357437.05 | J42: =J40*(1+Допущения!$C$6)*Допущения!$D$23 -> 245988.13 | ... AL42: =AL40*(1+Допущения!$C$6)*Допущения!$D$23 -> 1535076.8
A43: SMS и инфраструктура на билеты | B43: ₸ | C43: =C38/Допущения!$C$9*Допущения!$C$10+C38*Допущения!$C$11 -> 4752 | D43: =D38/Допущения!$C$9*Допущения!$C$10+D38*Допущения!$C$11 -> 6967.62 | E43: =E38/Допущения!$C$9*Допущения!$C$10+E38*Допущения!$C$11 -> 10218.077 | F43: =F38/Допущения!$C$9*Допущения!$C$10+F38*Допущения!$C$11 -> 22203.773 | G43: =G38/Допущения!$C$9*Допущения!$C$10+G38*Допущения!$C$11 -> 29859.063 | H43: =H38/Допущения!$C$9*Допущения!$C$10+H38*Допущения!$C$11 -> 38235.715 | I43: =I38/Допущения!$C$9*Допущения!$C$10+I38*Допущения!$C$11 -> 47280.033 | J43: =J38/Допущения!$C$9*Допущения!$C$10+J38*Допущения!$C$11 -> 32538.112 | ... AL43: =AL38/Допущения!$C$9*Допущения!$C$10+AL38*Допущения!$C$11 -> 203052.49
A44: Налог с выручки | B44: ₸ | C44: =C41*Допущения!$C$8 -> 3318.7968 | D44: =D41*Допущения!$C$8 -> 4866.1858 | E44: =E41*Допущения!$C$8 -> 7136.305 | F44: =F41*Допущения!$C$8 -> 15507.115 | G44: =G41*Допущения!$C$8 -> 20853.57 | H44: =H41*Допущения!$C$8 -> 26703.823 | I44: =I41*Допущения!$C$8 -> 33020.375 | J44: =J41*Допущения!$C$8 -> 22724.617 | ... AL44: =AL41*Допущения!$C$8 -> 141811.86
A45: Маржинальная прибыль | B45: ₸ | C45: =C41-C42-C43-C44 -> 38974.003 | D45: =D41-D42-D43-D44 -> 57145.632 | E45: =E41-E42-E43-E44 -> 83804.581 | F45: =F41-F42-F43-F44 -> 182106.46 | G45: =G41-G42-G43-G44 -> 244892.09 | H45: =H41-H42-H43-H44 -> 313594.04 | I45: =I41-I42-I43-I44 -> 387771.92 | J45: =J41-J42-J43-J44 -> 266864.58 | ... AL45: =AL41-AL42-AL43-AL44 -> 1665355.3
A46: Привлечение организаторов (CAC × новые) | B46: ₸ | C46: =C34*Допущения!$D$30 -> 450000 | D46: =D34*Допущения!$D$30 -> 450000 | E46: =E34*Допущения!$D$30 -> 450000 | F46: =F34*Допущения!$D$30 -> 450000 | G46: =G34*Допущения!$D$30 -> 450000 | H46: =H34*Допущения!$D$30 -> 450000 | I46: =I34*Допущения!$D$30 -> 450000 | J46: =J34*Допущения!$D$30 -> 450000 | ... AL46: =AL34*Допущения!$D$30 -> 1050000
A47: Хостинг и сервисы | B47: ₸ | C47: =CHOOSE(C$6,Допущения!$C$18,Допущения!$D$18,Допущения!$E$18) -> 60000 | D47: =CHOOSE(D$6,Допущения!$C$18,Допущения!$D$18,Допущения!$E$18) -> 60000 | E47: =CHOOSE(E$6,Допущения!$C$18,Допущения!$D$18,Допущения!$E$18) -> 60000 | F47: =CHOOSE(F$6,Допущения!$C$18,Допущения!$D$18,Допущения!$E$18) -> 60000 | G47: =CHOOSE(G$6,Допущения!$C$18,Допущения!$D$18,Допущения!$E$18) -> 60000 | H47: =CHOOSE(H$6,Допущения!$C$18,Допущения!$D$18,Допущения!$E$18) -> 60000 | I47: =CHOOSE(I$6,Допущения!$C$18,Допущения!$D$18,Допущения!$E$18) -> 60000 | J47: =CHOOSE(J$6,Допущения!$C$18,Допущения!$D$18,Допущения!$E$18) -> 60000 | ... AL47: =CHOOSE(AL$6,Допущения!$C$18,Допущения!$D$18,Допущения!$E$18) -> 200000
A48: Бухгалтерия, юрист, запуск | B48: ₸ | C48: =Допущения!$C$15+IF(C$4=1,Допущения!$C$14,0) -> 840000 | D48: =Допущения!$C$15+IF(D$4=1,Допущения!$C$14,0) -> 40000 | E48: =Допущения!$C$15+IF(E$4=1,Допущения!$C$14,0) -> 40000 | F48: =Допущения!$C$15+IF(F$4=1,Допущения!$C$14,0) -> 40000 | G48: =Допущения!$C$15+IF(G$4=1,Допущения!$C$14,0) -> 40000 | H48: =Допущения!$C$15+IF(H$4=1,Допущения!$C$14,0) -> 40000 | I48: =Допущения!$C$15+IF(I$4=1,Допущения!$C$14,0) -> 40000 | J48: =Допущения!$C$15+IF(J$4=1,Допущения!$C$14,0) -> 40000 | ... AL48: =Допущения!$C$15+IF(AL$4=1,Допущения!$C$14,0) -> 40000
A49: Выплата основателю | B49: ₸ | C49: =CHOOSE(C$6,Допущения!$C$19,Допущения!$D$19,Допущения!$E$19) -> 0 | D49: =CHOOSE(D$6,Допущения!$C$19,Допущения!$D$19,Допущения!$E$19) -> 0 | E49: =CHOOSE(E$6,Допущения!$C$19,Допущения!$D$19,Допущения!$E$19) -> 0 | F49: =CHOOSE(F$6,Допущения!$C$19,Допущения!$D$19,Допущения!$E$19) -> 0 | G49: =CHOOSE(G$6,Допущения!$C$19,Допущения!$D$19,Допущения!$E$19) -> 0 | H49: =CHOOSE(H$6,Допущения!$C$19,Допущения!$D$19,Допущения!$E$19) -> 0 | I49: =CHOOSE(I$6,Допущения!$C$19,Допущения!$D$19,Допущения!$E$19) -> 0 | J49: =CHOOSE(J$6,Допущения!$C$19,Допущения!$D$19,Допущения!$E$19) -> 0 | ... AL49: =CHOOSE(AL$6,Допущения!$C$19,Допущения!$D$19,Допущения!$E$19) -> 500000
A50: Постоянные расходы и маркетинг | B50: ₸ | C50: =SUM(C46:C49) -> 1350000 | D50: =SUM(D46:D49) -> 550000 | E50: =SUM(E46:E49) -> 550000 | F50: =SUM(F46:F49) -> 550000 | G50: =SUM(G46:G49) -> 550000 | H50: =SUM(H46:H49) -> 550000 | I50: =SUM(I46:I49) -> 550000 | J50: =SUM(J46:J49) -> 550000 | ... AL50: =SUM(AL46:AL49) -> 1790000
A51: Операционная прибыль | B51: ₸ | C51: =C45-C50 -> -1311026 | D51: =D45-D50 -> -492854.37 | E51: =E45-E50 -> -466195.42 | F51: =F45-F50 -> -367893.54 | G51: =G45-G50 -> -305107.91 | H51: =H45-H50 -> -236405.96 | I51: =I45-I50 -> -162228.08 | J51: =J45-J50 -> -283135.42 | ... AL51: =AL45-AL50 -> -124644.72
A52: Накопленный денежный поток | B52: ₸ | C52: =C51 -> -1311026 | D52: =C52+D51 -> -1803880.4 | E52: =D52+E51 -> -2270075.8 | F52: =E52+F51 -> -2637969.3 | G52: =F52+G51 -> -2943077.2 | H52: =G52+H51 -> -3179483.2 | I52: =H52+I51 -> -3341711.3 | J52: =I52+J51 -> -3624846.7 | K52: =J52+K51 -> -3844288.3 | ... AL52: =AK52+AL51 -> -14985208
A53: служебная: месяц с прибылью | C53: =IF(C51>0,C$4,"") | D53: =IF(D51>0,D$4,"") | E53: =IF(E51>0,E$4,"") | F53: =IF(F51>0,F$4,"") | G53: =IF(G51>0,G$4,"") | H53: =IF(H51>0,H$4,"") | I53: =IF(I51>0,I$4,"") | J53: =IF(J51>0,J$4,"") | ... AL53: =IF(AL51>0,AL$4,"")
A54: служебная: месяц с накопленным потоком ≥ 0 | C54: =IF(C52>=0,C$4,"") | D54: =IF(D52>=0,D$4,"") | E54: =IF(E52>=0,E$4,"") | F54: =IF(F52>=0,F$4,"") | G54: =IF(G52>=0,G$4,"") | H54: =IF(H52>=0,H$4,"") | I54: =IF(I52>=0,I$4,"") | J54: =IF(J52>=0,J$4,"") | ... AL54: =IF(AL52>=0,AL$4,"")
A57: Сценарий: Оптимистичный
A58: Новые организаторы | B58: шт. | C58: =CHOOSE(C$6,Допущения!$E$24,Допущения!$E$25,Допущения!$E$26) -> 5 | D58: =CHOOSE(D$6,Допущения!$E$24,Допущения!$E$25,Допущения!$E$26) -> 5 | E58: =CHOOSE(E$6,Допущения!$E$24,Допущения!$E$25,Допущения!$E$26) -> 5 | F58: =CHOOSE(F$6,Допущения!$E$24,Допущения!$E$25,Допущения!$E$26) -> 5 | G58: =CHOOSE(G$6,Допущения!$E$24,Допущения!$E$25,Допущения!$E$26) -> 5 | H58: =CHOOSE(H$6,Допущения!$E$24,Допущения!$E$25,Допущения!$E$26) -> 5 | I58: =CHOOSE(I$6,Допущения!$E$24,Допущения!$E$25,Допущения!$E$26) -> 5 | J58: =CHOOSE(J$6,Допущения!$E$24,Допущения!$E$25,Допущения!$E$26) -> 5 | ... AL58: =CHOOSE(AL$6,Допущения!$E$24,Допущения!$E$25,Допущения!$E$26) -> 11
A59: Ушедшие организаторы | B59: шт. | C59: =0 -> 0 | D59: =C60*Допущения!$E$27 -> 0.175 | E59: =D60*Допущения!$E$27 -> 0.343875 | F59: =E60*Допущения!$E$27 -> 0.50683937 | G59: =F60*Допущения!$E$27 -> 0.6641 | H59: =G60*Допущения!$E$27 -> 0.8158565 | I59: =H60*Допущения!$E$27 -> 0.96230152 | J59: =I60*Допущения!$E$27 -> 1.103621 | K59: =J60*Допущения!$E$27 -> 1.2399942 | ... AL59: =AK60*Допущения!$E$27 -> 6.2137299
A60: Активные организаторы на конец месяца | B60: шт. | C60: =C58 -> 5 | D60: =C60+D58-D59 -> 9.825 | E60: =D60+E58-E59 -> 14.481125 | F60: =E60+F58-F59 -> 18.974286 | G60: =F60+G58-G59 -> 23.310186 | H60: =G60+H58-H59 -> 27.494329 | I60: =H60+I58-I59 -> 31.532028 | J60: =I60+J58-J59 -> 35.428407 | K60: =J60+K58-K59 -> 39.188412 | ... AL60: =AK60+AL58-AL59 -> 182.32141
A61: Событий с продажей билетов | B61: шт. | C61: =C60*Допущения!$E$28*C$7 -> 6 | D61: =D60*Допущения!$E$28*D$7 -> 8.8425 | E61: =E60*Допущения!$E$28*E$7 -> 13.033012 | F61: =F60*Допущения!$E$28*F$7 -> 28.461428 | G61: =G60*Допущения!$E$28*G$7 -> 38.461806 | H61: =H60*Допущения!$E$28*H$7 -> 49.489792 | I61: =I60*Допущения!$E$28*I$7 -> 61.487454 | J61: =J60*Допущения!$E$28*J$7 -> 42.514088 | ... AL61: =AL60*Допущения!$E$28*AL$7 -> 273.48212
A62: Продано билетов | B62: шт. | C62: =C61*Допущения!$E$29 -> 900 | D62: =D61*Допущения!$E$29 -> 1326.375 | E62: =E61*Допущения!$E$29 -> 1954.9519 | F62: =F61*Допущения!$E$29 -> 4269.2143 | G62: =G61*Допущения!$E$29 -> 5769.2709 | H62: =H61*Допущения!$E$29 -> 7423.4689 | I62: =I61*Допущения!$E$29 -> 9223.1181 | J62: =J61*Допущения!$E$29 -> 6377.1132 | ... AL62: =AL61*Допущения!$E$29 -> 41022.317
A63: Платных билетов | B63: шт. | C63: =C62*(1-Допущения!$C$12) -> 810 | D63: =D62*(1-Допущения!$C$12) -> 1193.7375 | E63: =E62*(1-Допущения!$C$12) -> 1759.4567 | F63: =F62*(1-Допущения!$C$12) -> 3842.2928 | G63: =G62*(1-Допущения!$C$12) -> 5192.3438 | H63: =H62*(1-Допущения!$C$12) -> 6681.122 | I63: =I62*(1-Допущения!$C$12) -> 8300.8063 | J63: =J62*(1-Допущения!$C$12) -> 5739.4019 | ... AL63: =AL62*(1-Допущения!$C$12) -> 36920.086
A64: Оборот билетов организаторов (GMV) | B64: ₸ | C64: =C63*Допущения!$E$22 -> 5670000 | D64: =D63*Допущения!$E$22 -> 8356162.5 | E64: =E63*Допущения!$E$22 -> 12316197 | F64: =F63*Допущения!$E$22 -> 26896050 | G64: =G63*Допущения!$E$22 -> 36346407 | H64: =H63*Допущения!$E$22 -> 46767854 | I64: =I63*Допущения!$E$22 -> 58105644 | J64: =J63*Допущения!$E$22 -> 40175813 | ... AL64: =AL63*Допущения!$E$22 -> 2.584406e+08
A65: Выручка: сервисный сбор и комиссия | B65: ₸ | C65: =C64*(Допущения!$C$6+Допущения!$C$7)*(1-Допущения!$C$13) -> 274995 | D65: =D64*(Допущения!$C$6+Допущения!$C$7)*(1-Допущения!$C$13) -> 405273.88 | E65: =E64*(Допущения!$C$6+Допущения!$C$7)*(1-Допущения!$C$13) -> 597335.55 | F65: =F64*(Допущения!$C$6+Допущения!$C$7)*(1-Допущения!$C$13) -> 1304458.4 | G65: =G64*(Допущения!$C$6+Допущения!$C$7)*(1-Допущения!$C$13) -> 1762800.7 | H65: =H64*(Допущения!$C$6+Допущения!$C$7)*(1-Допущения!$C$13) -> 2268240.9 | I65: =I64*(Допущения!$C$6+Допущения!$C$7)*(1-Допущения!$C$13) -> 2818123.7 | J65: =J64*(Допущения!$C$6+Допущения!$C$7)*(1-Допущения!$C$13) -> 1948526.9 | ... AL65: =AL64*(Допущения!$C$6+Допущения!$C$7)*(1-Допущения!$C$13) -> 12534369
A66: Эквайринг | B66: ₸ | C66: =C64*(1+Допущения!$C$6)*Допущения!$E$23 -> 89302.5 | D66: =D64*(1+Допущения!$C$6)*Допущения!$E$23 -> 131609.56 | E66: =E64*(1+Допущения!$C$6)*Допущения!$E$23 -> 193980.1 | F66: =F64*(1+Допущения!$C$6)*Допущения!$E$23 -> 423612.79 | G66: =G64*(1+Допущения!$C$6)*Допущения!$E$23 -> 572455.91 | H66: =H64*(1+Допущения!$C$6)*Допущения!$E$23 -> 736593.7 | I66: =I64*(1+Допущения!$C$6)*Допущения!$E$23 -> 915163.89 | J66: =J64*(1+Допущения!$C$6)*Допущения!$E$23 -> 632769.06 | ... AL66: =AL64*(1+Допущения!$C$6)*Допущения!$E$23 -> 4070439.4
A67: SMS и инфраструктура на билеты | B67: ₸ | C67: =C62/Допущения!$C$9*Допущения!$C$10+C62*Допущения!$C$11 -> 13500 | D67: =D62/Допущения!$C$9*Допущения!$C$10+D62*Допущения!$C$11 -> 19895.625 | E67: =E62/Допущения!$C$9*Допущения!$C$10+E62*Допущения!$C$11 -> 29324.278 | F67: =F62/Допущения!$C$9*Допущения!$C$10+F62*Допущения!$C$11 -> 64038.214 | G67: =G62/Допущения!$C$9*Допущения!$C$10+G62*Допущения!$C$11 -> 86539.064 | H67: =H62/Допущения!$C$9*Допущения!$C$10+H62*Допущения!$C$11 -> 111352.03 | I67: =I62/Допущения!$C$9*Допущения!$C$10+I62*Допущения!$C$11 -> 138346.77 | J67: =J62/Допущения!$C$9*Допущения!$C$10+J62*Допущения!$C$11 -> 95656.698 | ... AL67: =AL62/Допущения!$C$9*Допущения!$C$10+AL62*Допущения!$C$11 -> 615334.76
A68: Налог с выручки | B68: ₸ | C68: =C65*Допущения!$C$8 -> 10999.8 | D68: =D65*Допущения!$C$8 -> 16210.955 | E68: =E65*Допущения!$C$8 -> 23893.422 | F68: =F65*Допущения!$C$8 -> 52178.337 | G68: =G65*Допущения!$C$8 -> 70512.029 | H68: =H65*Допущения!$C$8 -> 90729.636 | I68: =I65*Допущения!$C$8 -> 112724.95 | J68: =J65*Допущения!$C$8 -> 77941.077 | ... AL68: =AL65*Допущения!$C$8 -> 501374.76
A69: Маржинальная прибыль | B69: ₸ | C69: =C65-C66-C67-C68 -> 161192.7 | D69: =D65-D66-D67-D68 -> 237557.74 | E69: =E65-E66-E67-E68 -> 350137.75 | F69: =F65-F66-F67-F68 -> 764629.08 | G69: =G65-G66-G67-G68 -> 1033293.7 | H69: =H65-H66-H67-H68 -> 1329565.5 | I69: =I65-I66-I67-I68 -> 1651888.1 | J69: =J65-J66-J67-J68 -> 1142160.1 | ... AL69: =AL65-AL66-AL67-AL68 -> 7347220.1
A70: Привлечение организаторов (CAC × новые) | B70: ₸ | C70: =C58*Допущения!$E$30 -> 500000 | D70: =D58*Допущения!$E$30 -> 500000 | E70: =E58*Допущения!$E$30 -> 500000 | F70: =F58*Допущения!$E$30 -> 500000 | G70: =G58*Допущения!$E$30 -> 500000 | H70: =H58*Допущения!$E$30 -> 500000 | I70: =I58*Допущения!$E$30 -> 500000 | J70: =J58*Допущения!$E$30 -> 500000 | ... AL70: =AL58*Допущения!$E$30 -> 1100000
A71: Хостинг и сервисы | B71: ₸ | C71: =CHOOSE(C$6,Допущения!$C$18,Допущения!$D$18,Допущения!$E$18) -> 60000 | D71: =CHOOSE(D$6,Допущения!$C$18,Допущения!$D$18,Допущения!$E$18) -> 60000 | E71: =CHOOSE(E$6,Допущения!$C$18,Допущения!$D$18,Допущения!$E$18) -> 60000 | F71: =CHOOSE(F$6,Допущения!$C$18,Допущения!$D$18,Допущения!$E$18) -> 60000 | G71: =CHOOSE(G$6,Допущения!$C$18,Допущения!$D$18,Допущения!$E$18) -> 60000 | H71: =CHOOSE(H$6,Допущения!$C$18,Допущения!$D$18,Допущения!$E$18) -> 60000 | I71: =CHOOSE(I$6,Допущения!$C$18,Допущения!$D$18,Допущения!$E$18) -> 60000 | J71: =CHOOSE(J$6,Допущения!$C$18,Допущения!$D$18,Допущения!$E$18) -> 60000 | ... AL71: =CHOOSE(AL$6,Допущения!$C$18,Допущения!$D$18,Допущения!$E$18) -> 200000
A72: Бухгалтерия, юрист, запуск | B72: ₸ | C72: =Допущения!$C$15+IF(C$4=1,Допущения!$C$14,0) -> 840000 | D72: =Допущения!$C$15+IF(D$4=1,Допущения!$C$14,0) -> 40000 | E72: =Допущения!$C$15+IF(E$4=1,Допущения!$C$14,0) -> 40000 | F72: =Допущения!$C$15+IF(F$4=1,Допущения!$C$14,0) -> 40000 | G72: =Допущения!$C$15+IF(G$4=1,Допущения!$C$14,0) -> 40000 | H72: =Допущения!$C$15+IF(H$4=1,Допущения!$C$14,0) -> 40000 | I72: =Допущения!$C$15+IF(I$4=1,Допущения!$C$14,0) -> 40000 | J72: =Допущения!$C$15+IF(J$4=1,Допущения!$C$14,0) -> 40000 | ... AL72: =Допущения!$C$15+IF(AL$4=1,Допущения!$C$14,0) -> 40000
A73: Выплата основателю | B73: ₸ | C73: =CHOOSE(C$6,Допущения!$C$19,Допущения!$D$19,Допущения!$E$19) -> 0 | D73: =CHOOSE(D$6,Допущения!$C$19,Допущения!$D$19,Допущения!$E$19) -> 0 | E73: =CHOOSE(E$6,Допущения!$C$19,Допущения!$D$19,Допущения!$E$19) -> 0 | F73: =CHOOSE(F$6,Допущения!$C$19,Допущения!$D$19,Допущения!$E$19) -> 0 | G73: =CHOOSE(G$6,Допущения!$C$19,Допущения!$D$19,Допущения!$E$19) -> 0 | H73: =CHOOSE(H$6,Допущения!$C$19,Допущения!$D$19,Допущения!$E$19) -> 0 | I73: =CHOOSE(I$6,Допущения!$C$19,Допущения!$D$19,Допущения!$E$19) -> 0 | J73: =CHOOSE(J$6,Допущения!$C$19,Допущения!$D$19,Допущения!$E$19) -> 0 | ... AL73: =CHOOSE(AL$6,Допущения!$C$19,Допущения!$D$19,Допущения!$E$19) -> 500000
A74: Постоянные расходы и маркетинг | B74: ₸ | C74: =SUM(C70:C73) -> 1400000 | D74: =SUM(D70:D73) -> 600000 | E74: =SUM(E70:E73) -> 600000 | F74: =SUM(F70:F73) -> 600000 | G74: =SUM(G70:G73) -> 600000 | H74: =SUM(H70:H73) -> 600000 | I74: =SUM(I70:I73) -> 600000 | J74: =SUM(J70:J73) -> 600000 | ... AL74: =SUM(AL70:AL73) -> 1840000
A75: Операционная прибыль | B75: ₸ | C75: =C69-C74 -> -1238807.3 | D75: =D69-D74 -> -362442.26 | E75: =E69-E74 -> -249862.25 | F75: =F69-F74 -> 164629.08 | G75: =G69-G74 -> 433293.73 | H75: =H69-H74 -> 729565.54 | I75: =I69-I74 -> 1051888.1 | J75: =J69-J74 -> 542160.1 | ... AL75: =AL69-AL74 -> 5507220.1
A76: Накопленный денежный поток | B76: ₸ | C76: =C75 -> -1238807.3 | D76: =C76+D75 -> -1601249.6 | E76: =D76+E75 -> -1851111.8 | F76: =E76+F75 -> -1686482.7 | G76: =F76+G75 -> -1253189 | H76: =G76+H75 -> -523623.45 | I76: =H76+I75 -> 528264.66 | J76: =I76+J75 -> 1070424.8 | K76: =J76+K75 -> 1891724.1 | ... AL76: =AK76+AL75 -> 78607901
A77: служебная: месяц с прибылью | C77: =IF(C75>0,C$4,"") | D77: =IF(D75>0,D$4,"") | E77: =IF(E75>0,E$4,"") | F77: =IF(F75>0,F$4,"") -> 4 | G77: =IF(G75>0,G$4,"") -> 5 | H77: =IF(H75>0,H$4,"") -> 6 | I77: =IF(I75>0,I$4,"") -> 7 | J77: =IF(J75>0,J$4,"") -> 8 | ... AL77: =IF(AL75>0,AL$4,"") -> 36
A78: служебная: месяц с накопленным потоком ≥ 0 | C78: =IF(C76>=0,C$4,"") | D78: =IF(D76>=0,D$4,"") | E78: =IF(E76>=0,E$4,"") | F78: =IF(F76>=0,F$4,"") | G78: =IF(G76>=0,G$4,"") | H78: =IF(H76>=0,H$4,"") | I78: =IF(I76>=0,I$4,"") -> 7 | J78: =IF(J76>=0,J$4,"") -> 8 | ... AL78: =IF(AL76>=0,AL$4,"") -> 36

Sheet Сравнение моделей
A1: Почему процент с билета, а не подписка
A2: Объёмы базового сценария 3-го года из листа «План»; меняется только способ брать деньги. Подписку и гибрид предлагала исходная spec.md; выбран сервисный сбор (бизнес-решение 2026-10-02).
B4: Вводные для сравнения
B5: Подписка организатора, ₸ в месяц | C5: 25000 | G5: Альтернатива из spec.md; цена — допущение
B6: Гибрид: подписка, ₸ в месяц | C6: 15000
B7: Гибрид: комиссия с билета | C7: 0.01 | G7: spec.md: подписка + 1% с билета
B8: Доля организаторов, готовых платить подписку | C8: 0.5 | G8: Допущение: МСБ с редкими событиями не платит каждый месяц; процент без абонплаты берут все
B10: Объёмы базового сценария, 3-й год
B11: Организаторо-месяцев | C11: =SUM(План!$AA$36:$AL$36) -> 1036.9274
B12: Платных билетов | C12: =SUM(План!$AA$39:$AL$39) -> 117474.12
B13: Оборот билетов (GMV), ₸ | C13: =SUM(План!$AA$40:$AL$40) -> 7.0484471e+08
B15: Модель | C15: Выручка, ₸ | D15: Выручка на организатора в месяц, ₸ | E15: Кто платит
B16: Сервисный сбор 5% (выбрано) | C16: =C13*Допущения!$C$6*(1-Допущения!$C$13) -> 34184968 | D16: =IF($C$11=0,0,C16/$C$11) -> 32967.563 | E16: покупатель
B17: Подписка | C17: =C11*C8*C5 -> 12961592 | D17: =IF($C$11=0,0,C17/$C$11) -> 12500 | E17: организатор
B18: Гибрид: подписка + 1% | C18: =C11*C8*C6+C13*C7*(1-Допущения!$C$13) -> 14613949 | D18: =IF($C$11=0,0,C18/$C$11) -> 14093.513 | E18: организатор
B20: Точка равенства
B21: Платных билетов в месяц у организатора, при которых сбор = подписке | C21: =IF(Допущения!$D$22*Допущения!$C$6*(1-Допущения!$C$13)=0,0,C5/(Допущения!$D$22*Допущения!$C$6*(1-Допущения!$C$13))) -> 85.910653 | G21: меньше — организатору выгоднее процент (типичный МСБ), больше — подписка
B22: Платных билетов в месяц у организатора в базовом сценарии | C22: ='Юнит-экономика'!D15*(1-Допущения!$C$12) -> 111.87
B24: Вывод
B25: Сервисный сбор платит покупатель, поэтому организатору вход бесплатный — это главный аргумент для МСБ против крупных площадок, где обычно платят обе стороны (схема «10/10» у Ticketscloud: сбор с покупателя и комиссия с организатора). Подписка выгоднее только крупным организаторам с объёмом выше точки равенства, но их на старте нет, а у мелких она отсекает половину клиентов.

Sheet Рынок
A1: Рынок снизу вверх: МСБ-организаторы Казахстана
A2: Все численности — допущения для проверки порядка величин, их нужно подтвердить интервью и открытыми данными.
B4: Сегмент | C4: Организаторов | D4: Событий в год на одного | E4: Билетов на событие | F4: Средняя цена, ₸ | G4: Оборот в год, ₸ | H4: Наш сбор, ₸
B5: Стендап и камеди-клубы | C5: 60 | D5: 100 | E5: 80 | F5: 5000 | G5: =C5*D5*E5*F5 -> 2400000000 | H5: =G5*Допущения!$C$6 -> 120000000
B6: Небольшие концерты и клубные вечера | C6: 300 | D6: 24 | E6: 200 | F6: 7000 | G6: =C6*D6*E6*F6 -> 10080000000 | H6: =G6*Допущения!$C$6 -> 504000000
B7: Независимые театры и труппы | C7: 80 | D7: 60 | E7: 120 | F7: 5000 | G7: =C7*D7*E7*F7 -> 2880000000 | H7: =G7*Допущения!$C$6 -> 144000000
B8: Платные конференции и митапы | C8: 200 | D8: 6 | E8: 150 | F8: 15000 | G8: =C8*D8*E8*F8 -> 2700000000 | H8: =G8*Допущения!$C$6 -> 135000000
B9: Локальные фестивали | C9: 50 | D9: 2 | E9: 1500 | F9: 8000 | G9: =C9*D9*E9*F9 -> 1200000000 | H9: =G9*Допущения!$C$6 -> 60000000
B10: Мастер-классы, лекции, экскурсии | C10: 600 | D10: 24 | E10: 30 | F10: 4000 | G10: =C10*D10*E10*F10 -> 1728000000 | H10: =G10*Допущения!$C$6 -> 86400000
B11: Итого (доступный рынок) | C11: =SUM(C5:C10) -> 1290 | G11: =SUM(G5:G10) -> 20988000000 | H11: =SUM(H5:H10) -> 1049400000
B13: Доля рынка в 3-й год, базовый сценарий | C13: =IF(G11=0,0,SUM(План!$AA$40:$AL$40)/G11) -> 0.033583224
B14: Активных организаторов в конце 3-го года / всего в сегменте | C14: =IF(C11=0,0,План!AL36/C11) -> 0.079497489
B16: Проверка порядка величин: Ticketon
B17: Онлайн-заказов в месяц (2021) | C17: 42810 | D17: spec.md: оценка 2021 — выручка $6,1 млн, 42 810 онлайн-заказов в месяц, средний чек $11,9. Курс — допущение.
B18: Средний чек, $ | C18: 11.9
B19: Курс, ₸ за $ | C19: 480
B20: Оборот онлайн-заказов в год, ₸ | C20: =C17*C18*C19*12 -> 2934368640
B21: Доступный рынок МСБ к онлайн-обороту Ticketon, раз | C21: =IF(C20=0,0,G11/C20) -> 7.1524756 | D21: Больше 1: доступный рынок — все продажи сегмента, включая кассу, Instagram и Kaspi-переводы, а не только онлайн-билеты.
B22: Наш оборот 3-го года (база), % от онлайн-оборота Ticketon 2021 | C22: =IF(C20=0,0,SUM(План!$AA$40:$AL$40)/C20) -> 0.24020319

Sheet Риски и источники
A1: Риски модели и источники
A3: Риск | B3: Описание и что делать
A4: Приём денег за организаторов | B4: Если оплата за билеты проходит через нас и потом выплачивается организатору, это может требовать регистрации платёжной организации в Нацбанке РК (Закон «О платежах и платёжных системах»). Альтернатива — сплит-платёж эквайера (деньги сразу делятся между организатором и нами); в MVP сплит-платежи исключены (CLAUDE.md). Проверить с юристом до запуска.
A5: Налоговая база | B5: Налог 4% считается только с нашего сбора при агентской схеме (договор с организатором, мы — агент). Без неё налоговой базой может считаться весь оборот билетов — модель тогда неверна.
A6: Ставка сбора | B6: При 5% базовый сценарий за три года не окупается: маржа с билета около 120 ₸, а эквайринг берётся со всей суммы оплаты и от ставки не зависит. Окупаемость за три года даёт ставка около 7%. Ставка — настройка продукта (SERVICE_FEE_BPS), её можно менять без кода; старые заказы сохраняют свой сбор.
A7: Численности рынка | B7: Число организаторов по сегментам — допущения; нужны интервью с 10–20 организаторами.
A8: Конкуренты | B8: Ticketon и kino.kz могут снизить сбор для МСБ; наш ответ — бесплатный вход и своя схема зала.
A11: Источники
A12: Сервисный сбор ~10%, «10/10» | B12: https://support.ticketscloud.com/ (инструкция для организаторов, условия сделок)
A13: Эквайринг Kaspi Pay | B13: https://guide.kaspi.kz/partner/ru/account/opening/q258
A14: Эквайринг Halyk ePay | B14: https://halykbank.kz/en/business/payment/epay
A15: Сравнение эквайринга, 2026 | B15: https://finkaz.kz/acquiring
A16: Упрощённый режим 4% с 2026 | B16: https://digitalbusiness.kz/2025-08-07/uznali-kogda-objyavyat-stavki-po-novoy-uproshchenke-na-2026-god/
A17: Ticketon, ориентир 2021 | B17: docs/spec.md, раздел «Бизнес-модель»
